continuous.py
setup.py
continuously.egg-info/PKG-INFO
continuously.egg-info/SOURCES.txt
continuously.egg-info/dependency_links.txt
continuously.egg-info/entry_points.txt
continuously.egg-info/requires.txt
continuously.egg-info/top_level.txt