Metadata-Version: 1.0
Name: continuously
Version: 0.0.1
Summary: Allows to call a command continuously, whenever an argument file changes
Home-page: UNKNOWN
Author: Francesco Bruschi
Author-email: Bruschi@elet.polimi.it
License: UNKNOWN
Platform: UNKNOWN
